vizq/__init__.py
vizq/__main__.py
vizq/visualization.py
vizq-0.5.0.dist-info/METADATA
vizq-0.5.0.dist-info/WHEEL
vizq-0.5.0.dist-info/RECORD
