Metadata-Version: 2.1
Name: vizq
Version: 0.5.0
Summary: 
Author: e-panzarasa
Author-email: ezequiel.panzarasa@qubika.com
Requires-Python: >=3.9.1,<4.0.0
Classifier: Programming Language :: Python :: 3
Classifier: Programming Language :: Python :: 3.10
Classifier: Programming Language :: Python :: 3.11
Classifier: Programming Language :: Python :: 3.12
Requires-Dist: matplotlib (>=3.8.2,<4.0.0)
Requires-Dist: numpy (>=1.26.3,<2.0.0)
Requires-Dist: pandas (>=2.1.4,<3.0.0)
